<beans xmlns="http://www.springframework.org/schema/beans"
	xmlns:xsi="http://www.w3.org/2001/XMLSchema-instance"
	xsi:schemaLocation="http://www.springframework.org/schema/beans
   http://www.springframework.org/schema/beans/spring-beans.xsd">
   <bean id="empdao" class="employeemanagement.employeeDao">
   <property name="jdbcDriver" value="com.mysql.jdbc.Driver"></property>
   <property name="url"  value="jdbc:mysql://localhost/jdbcassignment"></property>
   <property name="user" value="root"></property>
   <property name="password" value=""></property>
   </bean>
  
  </beans>